{
  "id": "dee53b28-1c8e-4b49-bcd0-ade3b518bf01",
  "prevId": "d0c91dad-9788-4eeb-ad60-24d9b9cd7bc0",
  "version": "5",
  "dialect": "pg",
  "tables": {
    "blocks": {
      "name": "blocks",
      "schema": "",
      "columns": {
        "id": {
          "name": "id",
          "type": "serial",
          "primaryKey": true,
          "notNull": true
        },
        "edition": {
          "name": "edition",
          "type": "varchar",
          "primaryKey": false,
          "notNull": true,
          "default": "date_part('year', CURRENT_DATE)"
        },
        "type": {
          "name": "type",
          "type": "block",
          "primaryKey": false,
          "notNull": true
        },
        "is_active": {
          "name": "is_active",
          "type": "boolean",
          "primaryKey": false,
          "notNull": true,
          "default": true
        },
        "start": {
          "name": "start",
          "type": "timestamp",
          "primaryKey": false,
          "notNull": true
        },
        "end": {
          "name": "end",
          "type": "timestamp",
          "primaryKey": false,
          "notNull": true
        },
        "created_at": {
          "name": "created_at",
          "type": "timestamp",
          "primaryKey": false,
          "notNull": true,
          "default": "CURRENT_TIMESTAMP"
        },
        "updated_at": {
          "name": "updated_at",
          "type": "timestamp",
          "primaryKey": false,
          "notNull": false
        }
      },
      "indexes": {
        "start_idx": {
          "name": "start_idx",
          "columns": ["start"],
          "isUnique": false
        }
      },
      "foreignKeys": {},
      "compositePrimaryKeys": {},
      "uniqueConstraints": {
        "blocks_start_unique": {
          "name": "blocks_start_unique",
          "nullsNotDistinct": false,
          "columns": ["start"]
        }
      }
    },
    "events": {
      "name": "events",
      "schema": "",
      "columns": {
        "id": {
          "name": "id",
          "type": "serial",
          "primaryKey": true,
          "notNull": true
        },
        "block_id": {
          "name": "block_id",
          "type": "serial",
          "primaryKey": false,
          "notNull": true
        },
        "title": {
          "name": "title",
          "type": "varchar",
          "primaryKey": false,
          "notNull": true
        },
        "description": {
          "name": "description",
          "type": "varchar",
          "primaryKey": false,
          "notNull": false
        },
        "location": {
          "name": "location",
          "type": "location",
          "primaryKey": false,
          "notNull": true,
          "default": "'UNASSIGNED'"
        },
        "image_url": {
          "name": "image_url",
          "type": "varchar",
          "primaryKey": false,
          "notNull": false
        },
        "link_url": {
          "name": "link_url",
          "type": "varchar",
          "primaryKey": false,
          "notNull": false
        },
        "link_label": {
          "name": "link_label",
          "type": "varchar",
          "primaryKey": false,
          "notNull": false
        },
        "category": {
          "name": "category",
          "type": "category",
          "primaryKey": false,
          "notNull": true,
          "default": "'OTHER'"
        },
        "created_at": {
          "name": "created_at",
          "type": "timestamp",
          "primaryKey": false,
          "notNull": true,
          "default": "CURRENT_TIMESTAMP"
        },
        "updated_at": {
          "name": "updated_at",
          "type": "timestamp",
          "primaryKey": false,
          "notNull": false
        }
      },
      "indexes": {},
      "foreignKeys": {
        "events_block_id_blocks_id_fk": {
          "name": "events_block_id_blocks_id_fk",
          "tableFrom": "events",
          "tableTo": "blocks",
          "columnsFrom": ["block_id"],
          "columnsTo": ["id"],
          "onDelete": "cascade",
          "onUpdate": "no action"
        }
      },
      "compositePrimaryKeys": {},
      "uniqueConstraints": {}
    },
    "speakers": {
      "name": "speakers",
      "schema": "",
      "columns": {
        "id": {
          "name": "id",
          "type": "serial",
          "primaryKey": true,
          "notNull": true
        },
        "event_id": {
          "name": "event_id",
          "type": "serial",
          "primaryKey": false,
          "notNull": true
        },
        "first_name": {
          "name": "first_name",
          "type": "varchar",
          "primaryKey": false,
          "notNull": true
        },
        "last_name": {
          "name": "last_name",
          "type": "varchar",
          "primaryKey": false,
          "notNull": true
        },
        "title": {
          "name": "title",
          "type": "varchar",
          "primaryKey": false,
          "notNull": false
        },
        "pronouns": {
          "name": "pronouns",
          "type": "varchar",
          "primaryKey": false,
          "notNull": false
        },
        "email": {
          "name": "email",
          "type": "varchar",
          "primaryKey": false,
          "notNull": false
        },
        "organization": {
          "name": "organization",
          "type": "varchar",
          "primaryKey": false,
          "notNull": false
        },
        "image_url": {
          "name": "image_url",
          "type": "varchar",
          "primaryKey": false,
          "notNull": false
        },
        "bio": {
          "name": "bio",
          "type": "varchar",
          "primaryKey": false,
          "notNull": false
        },
        "created_at": {
          "name": "created_at",
          "type": "timestamp",
          "primaryKey": false,
          "notNull": true,
          "default": "CURRENT_TIMESTAMP"
        },
        "updated_at": {
          "name": "updated_at",
          "type": "timestamp",
          "primaryKey": false,
          "notNull": false
        }
      },
      "indexes": {},
      "foreignKeys": {
        "speakers_event_id_events_id_fk": {
          "name": "speakers_event_id_events_id_fk",
          "tableFrom": "speakers",
          "tableTo": "events",
          "columnsFrom": ["event_id"],
          "columnsTo": ["id"],
          "onDelete": "cascade",
          "onUpdate": "no action"
        }
      },
      "compositePrimaryKeys": {},
      "uniqueConstraints": {}
    }
  },
  "enums": {
    "block": {
      "name": "block",
      "values": {
        "SPEAKER": "SPEAKER",
        "LIGHTENING": "LIGHTENING",
        "LIGHTNING": "LIGHTNING",
        "PAUSE": "PAUSE",
        "ANNOUNCEMENT": "ANNOUNCEMENT",
        "NETWORKING": "NETWORKING",
        "UNCONF": "UNCONF"
      }
    },
    "category": {
      "name": "category",
      "values": {
        "ACADEMIA": "ACADEMIA",
        "ACCESSIBILITY": "ACCESSIBILITY",
        "CAREER": "CAREER",
        "DASHBOARD": "DASHBOARD",
        "ANALYTICS": "ANALYTICS",
        "ART": "ART",
        "SCIENCE": "SCIENCE",
        "LITERACY": "LITERACY",
        "DEMO": "DEMO",
        "DESIGN": "DESIGN",
        "HISTORICAL": "HISTORICAL",
        "JOURNALISM": "JOURNALISM",
        "MAPS": "MAPS",
        "PROCESS": "PROCESS",
        "PROGRAMMING": "PROGRAMMING",
        "PROJECT": "PROJECT",
        "RESEARCH": "RESEARCH",
        "SOCIAL": "SOCIAL",
        "SPORTS": "SPORTS",
        "STORYTELLING": "STORYTELLING",
        "THEORY": "THEORY",
        "TOOLING": "TOOLING",
        "INDUSTRY": "INDUSTRY",
        "UNCERTAINTY": "UNCERTAINTY",
        "UNUSUAL": "UNUSUAL",
        "OTHER": "OTHER",
        "KEYNOTE": "KEYNOTE",
        "DVS": "DVS"
      }
    },
    "location": {
      "name": "location",
      "values": {
        "UNASSIGNED": "UNASSIGNED",
        "ROOM1": "ROOM1",
        "ROOM2": "ROOM2",
        "ROOM3": "ROOM3",
        "ROOM4": "ROOM4",
        "VIRTUAL": "VIRTUAL",
        "MAIN": "MAIN",
        "ZOOM": "ZOOM",
        "SLACK": "SLACK"
      }
    }
  },
  "schemas": {},
  "_meta": {
    "columns": {},
    "schemas": {},
    "tables": {}
  }
}
